json_logic/__init__.py
json_logic/py.typed
json_logic/typing.py
json_logic/meta/__init__.py
json_logic/meta/base.py
json_logic/meta/expressions.py
json_logic/meta/operations.py
maykin_json_logic_py-0.13.0.dist-info/LICENSE
maykin_json_logic_py-0.13.0.dist-info/METADATA
maykin_json_logic_py-0.13.0.dist-info/WHEEL
maykin_json_logic_py-0.13.0.dist-info/top_level.txt
maykin_json_logic_py-0.13.0.dist-info/RECORD
