Metadata-Version: 2.1
Name: maykin-json-logic-py
Version: 0.13.0
Summary: Build complex rules, serialize them as JSON, and execute them in Python
Home-page: https://github.com/maykinmedia/json-logic-py
Author: nadir.izr,maykin
Author-email: nadir@soundmindtech.com,support@maykinmedia.nl
License: MIT
Keywords: jsonLogic
Classifier: Development Status :: 3 - Alpha
Classifier: Intended Audience :: Developers
Classifier: Operating System :: Unix
Classifier: Operating System :: MacOS
Classifier: Operating System :: Microsoft :: Windows
Classifier: Programming Language :: Python :: 3.10
Classifier: Programming Language :: Python :: 3.11
Classifier: Topic :: Software Development :: Libraries :: Python Modules
License-File: LICENSE
Requires-Dist: isodate
Provides-Extra: coverage
Requires-Dist: coverage ; extra == 'coverage'
Provides-Extra: pep8
Requires-Dist: flake8 ; extra == 'pep8'
Provides-Extra: release
Requires-Dist: bumpversion ; extra == 'release'
Requires-Dist: twine ; extra == 'release'
Provides-Extra: tests
Requires-Dist: tox ; extra == 'tests'
Requires-Dist: pytest-cov ; extra == 'tests'
Requires-Dist: freezegun ; extra == 'tests'
Requires-Dist: isort ; extra == 'tests'
Requires-Dist: black ; extra == 'tests'
Requires-Dist: flake8 ; extra == 'tests'
Requires-Dist: coverage ; extra == 'tests'
